getmeta/__init__.py
getmeta/__main__.py
getmeta/cli.py
getmeta-2024.5.26.dist-info/LICENSE
getmeta-2024.5.26.dist-info/METADATA
getmeta-2024.5.26.dist-info/WHEEL
getmeta-2024.5.26.dist-info/entry_points.txt
getmeta-2024.5.26.dist-info/top_level.txt
getmeta-2024.5.26.dist-info/RECORD
