Metadata-Version: 2.1
Name: getmeta
Version: 2024.5.26
Summary: Not just gold builds anymore!
Home-page: https://github.com/4n6ir/getmeta
Author: John Lukach
Author-email: hello@4n6ir.com
License: Apache-2.0
Requires-Python: >=3.8
License-File: LICENSE
Requires-Dist: requests
